zipml/__init__.py
zipml/helpers.py
zipml/zipml.py
zipml/data/__init__.py
zipml/data/file_operations.py
zipml/data/preprocessing/__init__.py
zipml/data/preprocessing/encoding.py
zipml/data/preprocessing/split_data.py
zipml/model/__init__.py
zipml/model/analyze_model_predictions.py
zipml/model/calculate_model_results.py
zipml/model/measure_prediction_time.py
zipml/utils/__init__.py
zipml/utils/calculate_sentence_length_percentile.py
zipml/utils/read_time_series_data.py
zipml/virtualization/__init__.py
zipml/virtualization/combine_and_plot_model_results.py
zipml/virtualization/plot_random_image.py
zipml/virtualization/plot_time_series.py
zipml/virtualization/save_and_plot_confusion_matrix.py
zipml/visualization/__init__.py
zipml/visualization/combine_and_plot_model_results.py
zipml/visualization/plot_random_image.py
zipml/visualization/plot_time_series.py
zipml/visualization/save_and_plot_confusion_matrix.py
zipml-0.2.5.dist-info/LICENSE
zipml-0.2.5.dist-info/METADATA
zipml-0.2.5.dist-info/WHEEL
zipml-0.2.5.dist-info/entry_points.txt
zipml-0.2.5.dist-info/top_level.txt
zipml-0.2.5.dist-info/RECORD
