Metadata-Version: 2.1
Name: zipml
Version: 0.2.5
Summary: A simple AutoML tool for small datasets with useful helper functions
Home-page: https://github.com/abdozmantar/zipml
Author: Abdullah OZMANTAR
Author-email: abdullahozmntr@gmail.com
Classifier: Development Status :: 3 - Alpha
Classifier: Intended Audience :: Developers
Classifier: Intended Audience :: Education
Classifier: Topic :: Software Development :: Libraries
Classifier: Programming Language :: Python :: 3
Classifier: Programming Language :: Python :: 3.11
Classifier: License :: OSI Approved :: MIT License
Classifier: Operating System :: OS Independent
Requires-Python: >=3.6
License-File: LICENSE
Requires-Dist: pandas>=1.0.0
Requires-Dist: scikit-learn>=0.22
Requires-Dist: matplotlib>=3.0.0
Requires-Dist: seaborn>=0.9.0
